sqlite_vec_sqlalchemy/__init__.py
sqlite_vec_sqlalchemy-0.1.0.dist-info/METADATA
sqlite_vec_sqlalchemy-0.1.0.dist-info/WHEEL
sqlite_vec_sqlalchemy-0.1.0.dist-info/RECORD
