Metadata-Version: 2.4
Name: sqlite-vec-sqlalchemy
Version: 0.1.0
Summary: Add your description here
Requires-Python: >=3.8
Requires-Dist: sqlalchemy>=2.0.0
Requires-Dist: sqlite-vec>=0.1.6
